rhubarb/__init__.py
rhubarb/config.py
rhubarb/construct.py
rhubarb/core.py
rhubarb/crud.py
rhubarb/env.py
rhubarb/errors.py
rhubarb/extension.py
rhubarb/fixtures.py
rhubarb/functions.py
rhubarb/local_cache.py
rhubarb/migrations/__init__.py
rhubarb/migrations/cmd/__init__.py
rhubarb/migrations/cmd/apply.py
rhubarb/migrations/cmd/make.py
rhubarb/migrations/cmd/reset.py
rhubarb/migrations/data.py
rhubarb/migrations/models.py
rhubarb/migrations/utils.py
rhubarb/model.py
rhubarb/object_set.py
rhubarb/password.py
rhubarb/permission_classes.py
rhubarb/pkg/__init__.py
rhubarb/pkg/arq/__init__.py
rhubarb/pkg/arq/config.py
rhubarb/pkg/arq/worker.py
rhubarb/pkg/audit/__init__.py
rhubarb/pkg/audit/config.py
rhubarb/pkg/audit/extensions.py
rhubarb/pkg/audit/models.py
rhubarb/pkg/email/__init__.py
rhubarb/pkg/email/config.py
rhubarb/pkg/email/send.py
rhubarb/pkg/postgres/__init__.py
rhubarb/pkg/postgres/config.py
rhubarb/pkg/postgres/connection.py
rhubarb/pkg/postgres/connection_base.py
rhubarb/pkg/redis/__init__.py
rhubarb/pkg/redis/cache.py
rhubarb/pkg/redis/config.py
rhubarb/pkg/redis/connection.py
rhubarb/pkg/redis/rate_limit.py
rhubarb/pkg/sessions/__init__.py
rhubarb/pkg/sessions/config.py
rhubarb/pkg/sessions/middleware.py
rhubarb/pkg/starlette/__init__.py
rhubarb/pkg/starlette/applications.py
rhubarb/pkg/starlette/config.py
rhubarb/pkg/starlette/middleware.py
rhubarb/pkg/users/__init__.py
rhubarb/pkg/users/backends.py
rhubarb/pkg/users/config.py
rhubarb/pkg/users/impersonate.py
rhubarb/pkg/users/middleware.py
rhubarb/pkg/users/models.py
rhubarb/pkg/webauthn/__init__.py
rhubarb/pkg/webauthn/client.py
rhubarb/pkg/webauthn/config.py
rhubarb/pkg/webauthn/models.py
rhubarb/schema.py
rhubarb_graphql-0.1.0.dist-info/LICENSE.txt
rhubarb_graphql-0.1.0.dist-info/METADATA
rhubarb_graphql-0.1.0.dist-info/WHEEL
rhubarb_graphql-0.1.0.dist-info/RECORD
