Metadata-Version: 2.1
Name: rhubarb-graphql
Version: 0.1.0
Summary: Rhubarb is an experimental ORM baked from scratch focused on automatic optimizations with Postgres data using GQL.
Home-page: https://www.rhubarb.rocks
License: MIT
Author: Kyle Hanson
Author-email: me@khanson.io
Requires-Python: >=3.11,<4.0
Classifier: License :: OSI Approved :: MIT License
Classifier: Programming Language :: Python :: 3
Classifier: Programming Language :: Python :: 3.11
Requires-Dist: aiosmtplib (>=2.0.1,<3.0.0)
Requires-Dist: arq (>=0.25.0,<0.26.0)
Requires-Dist: asgiref (>=3.6.0,<4.0.0)
Requires-Dist: bcrypt (>=4.0.1,<5.0.0)
Requires-Dist: cachetools (>=5.3.0,<6.0.0)
Requires-Dist: httpx (>=0.24.0,<0.25.0)
Requires-Dist: phonenumbers (>=8.13.11,<9.0.0)
Requires-Dist: psycopg (>=3.1.8,<4.0.0)
Requires-Dist: psycopg-pool (>=3.1.7,<4.0.0)
Requires-Dist: pytest-asyncio (>=0.21.0,<0.22.0)
Requires-Dist: redis (>=4.5.4,<5.0.0)
Requires-Dist: starlette-session (>=0.4.3,<0.5.0)
Requires-Dist: strawberry-graphql (>=0.174.0,<0.175.0)
Requires-Dist: webauthn (>=1.8.1,<2.0.0)
Project-URL: Repository, https://github.com/hansonkd/rhubarb/
